{
 "cite": "Tex. Const. art. VIII, \u00a723",
 "heading": "STATEWIDE APPRAISAL OF REAL PROPERTY FOR AD VALOREM TAX PURPOSES PROHIBITED; ENFORCEMENT OF APPRAISAL STANDARDS AND PROCEDURES",
 "operative_text": "(a) There shall be no statewide appraisal of real property for ad valorem tax purposes; however, this shall not preclude formula distribution of tax revenues to political subdivisions of the state.\n(b) Administrative and judicial enforcement of uniform standards and procedures for appraisal of property for ad valorem tax purposes shall be prescribed by general law.",
 "cross_refs": [],
 "defined_terms": [],
 "_note": null
}