{
 "cite": "Tex. Const. art. VIII, \u00a77-b",
 "heading": "USE OF REVENUES FROM FEDERAL REIMBURSEMENT",
 "operative_text": "All revenues received from the federal government as reimbursement for state expenditures of funds that are themselves dedicated for acquiring rights-of-way and constructing, maintaining, and policing public roadways are also constitutionally dedicated and shall be used only for those purposes.",
 "cross_refs": [],
 "defined_terms": [],
 "_note": "No defined terms or cross-references present in source text."
}