{
 "cite": "Educ. Code \u00a733.0832",
 "heading": "EQUAL OPPORTUNITY FOR CERTAIN STUDENTS TO PARTICIPATE IN UNIVERSITY INTERSCHOLASTIC LEAGUE ACTIVITIES",
 "operative_text": "Except as provided by Subsections (c-2) and (i), a public school that participates in an activity sponsored by the league shall provide a non-enrolled student, who otherwise meets league eligibility standards to represent that school in a league activity, with the opportunity to participate in the activity on behalf of the school in the same manner that the school provides the opportunity to participate to students enrolled in the school.",
 "cross_refs": [
  "Educ. Code \u00a729.916(a)(1)",
  "Educ. Code \u00a725.001",
  "Educ. Code \u00a738.001"
 ],
 "defined_terms": [
  {
   "term": "League",
   "definition_excerpt": "\"League\" means the University Interscholastic League."
  },
  {
   "term": "Non-enrolled student",
   "definition_excerpt": "\"Non-enrolled student\" means a student who receives instruction as described by Section 29.916(a)(1) from a nonpublic school."
  }
 ],
 "_note": "Full section extracted. Includes subsections (a) through (m). Statute added by Acts 2021, 87th Leg., R.S., Ch. 996 (H.B. 547), Sec. 1, eff. September 1, 2021; amended by Acts 2023, 88th Leg., R.S., Ch. 483 (H.B. 699), Sec. 1, eff. June 10, 2023, and Acts 2025, 89th Leg., R.S., Ch. 770 (S.B. 401), Sec. 1, eff. June 20, 2025."
}