{
 "cite": "Educ. Code \u00a748.257",
 "heading": "LOCAL REVENUE LEVEL IN EXCESS OF ENTITLEMENT",
 "operative_text": "(a) Subject to Subsection (b), if a school district's tier one local share under Section 48.256 exceeds the district's entitlement under Section 48.266(a)(1) less the district's distribution from the state available school fund, the district must reduce the district's tier one revenue level in accordance with Chapter 49 to a level not to exceed the district's entitlement under Section 48.266(a)(1) less the district's distribution from the state available school fund. (b) This subsection applies only to a school district to which Subsection (a) applies. If a district's maintenance and operations tax collections from the tax rate described by Section 45.0032(a) for the current tax year minus the required reduction in a district's tier one revenue level under Subsection (a) results in an amount that is less than the amount of the district's entitlement under Section 48.266(a)(1) less the district's distribution from the state available school fund, the agency shall adjust the amount of the reduction required in the district's tier one revenue level under Subsection (a) up to the amount of local funds necessary for the district's entitlement under Section 48.266(a)(1) less the district's distribution from the state available school fund. (b-1) If for any school year a school district receives an adjustment under Subsection (b) and, after that adjustment, is no longer subject to Subsection (a), the district is entitled to additional state aid for that school year in an amount equal to the lesser of: (1) the difference, if the difference is greater than zero, between: (A) the amount to which the district is entitled under Subchapters B, C, and D less the district's distribution from the available school fund for that school year; and (B) the district's tier one maintenance and operations tax collections for that school year; or (2) the district's allotment under Section 48.158 for that school year. (c) For purposes of Subsection (a), state aid to which a district is entitled under this chapter that is not described by Section 48.266(a)(3) may offset the amount by which a district must reduce the district's revenue level under this section. Any amount of state aid used as an offset under this subsection shall reduce the amount of state aid to which the district is entitled. (d) Except as provided by Subsection (e), a school district is entitled to retain the total amount of the district's tier two local share described by Section 48.266(a)(5)(A). (e) In any school year for which the amount of state funds appropriated specifically excludes the amount necessary to provide the dollar amount guaranteed level of state and local funds per weighted student per cent of tax effort under Section 48.202(a-1)(1), a district may only retain the amount of the district's tier two local share described by Section 48.266(a)(5)(A) equal to the amount of revenue that would be generated based on the amount appropriated for the dollar amount guaranteed level of state and local funds. (f) If the amount of a school district's tier two local share described by Section 48.266(a)(5)(B) to which a district is entitled exceeds the amount described by Section 48.202(a-1)(2), the district must reduce the district's revenue in accordance with Chapter 49 to a level not to exceed the amount described by Section 48.202 (a-1)(2). (g) For a district to which Section 45.003(f) applies, revenue generated from any cents of maintenance and operations tax effort that exceeds the maximum rate permitted under Section 45.003(d) is subject to the revenue limit established under Subsection (f).",
 "cross_refs": [
  "Educ. Code \u00a748.256",
  "Educ. Code \u00a748.266(a)(1)",
  "Educ. Code ch. 49",
  "Educ. Code \u00a745.0032(a)",
  "Educ. Code ch. 48 subch. B",
  "Educ. Code ch. 48 subch. C",
  "Educ. Code ch. 48 subch. D",
  "Educ. Code \u00a748.158",
  "Educ. Code \u00a748.266(a)(3)",
  "Educ. Code \u00a748.266(a)(5)(A)",
  "Educ. Code \u00a748.202(a-1)(1)",
  "Educ. Code \u00a748.266(a)(5)(B)",
  "Educ. Code \u00a748.202(a-1)(2)",
  "Educ. Code \u00a745.003(f)",
  "Educ. Code \u00a745.003(d)"
 ],
 "defined_terms": [],
 "_note": "No explicit statutory definitions found in this section. Subchapters B, C, and D in subsection (b-1) are presumed to be within Chapter 48 (\"this chapter\")."
}