{
 "cite": "Educ. Code \u00a748.268",
 "heading": "ADJUSTMENT FOR RESOLUTION OF DISPUTE OR ERROR RESULTING IN TAXATION OF SAME PROPERTY BY MULTIPLE SCHOOL DISTRICTS",
 "operative_text": "The commissioner shall adjust the amounts due to a school district under this chapter and Chapter 46 as necessary to account for the resolution of a dispute or error involving the district and another district by an agreement between the districts entered into under Section 31.112(c), Tax Code, or by a final order of the supreme court entered under Section 72.010, Local Government Code.",
 "cross_refs": [
  "Tax Code \u00a731.112(c)",
  "Loc. Gov't Code \u00a772.010",
  "Educ. Code Ch. 46"
 ],
 "defined_terms": [],
 "_note": ""
}