{
 "cite": "Educ. Code \u00a712.254",
 "heading": "ADVISORY COMMITTEE",
 "operative_text": "An advisory committee is established to make recommendations to the commissioner regarding: (1) the secondary exit-level assessment tool adopted or developed under Section 12.260 and the satisfactory performance level for that tool; and (2) the accountability frameworks adopted under Section 12.262, including the performance domains and measures in each framework.",
 "cross_refs": [
  "Educ. Code \u00a712.260",
  "Educ. Code \u00a712.262",
  "Educ. Code \u00a729.259"
 ],
 "defined_terms": [],
 "_note": null
}