{
 "cite": "Educ. Code \u00a721.903",
 "heading": "PREPARING AND RETAINING EDUCATORS THROUGH PARTNERSHIP TRADITIONAL PRESERVICE PROGRAM",
 "operative_text": "The commissioner shall establish the Preparing and Retaining Educators through Partnership Traditional Preservice Program as a partnership preservice program to enable qualified educator preparation programs, as determined by the commissioner, that meet the traditional teacher preparation requirements under Section 21.04421 to form partnerships with school districts or open-enrollment charter schools to help prepare candidates for a standard certificate.",
 "cross_refs": [
  "Educ. Code \u00a721.04421",
  "Educ. Code \u00a721.902",
  "Educ. Code \u00a748.157(b)(1)",
  "Educ. Code \u00a748.157"
 ],
 "defined_terms": [],
 "_note": ""
}