{
 "cite": "Educ. Code \u00a711.054",
 "heading": "ELECTING TRUSTEES BY CUMULATIVE VOTING",
 "operative_text": "The board of trustees of an independent school district that elects its trustees at large or at large by position may order that elections for trustees be held using the cumulative voting procedure described by this section.",
 "cross_refs": [
  "Educ. Code \u00a711.058"
 ],
 "defined_terms": [],
 "_note": "No defined terms explicitly defined in this section. Cross reference to Section 11.058 found in subsection (g)."
}