{
 "cite": "Educ. Code \u00a711.1518",
 "heading": "TRUSTEE INFORMATION",
 "operative_text": "(a) Each school district that maintains an Internet website shall post on the website the name, e-mail address, and term of office, including the date the term began and the date the term expires, of each member of the district's board of trustees. (b) If a school district does not maintain an Internet website, the district shall submit the information required by Subsection (a) to the agency. On receipt of the district's information, the agency shall post the information on the agency's Internet website. (c) Not later than the 30th day after a new person is sworn in as a member of a school district's board of trustees, the district shall update the information required under Subsection (a) and, as applicable: (1) post the updated information on the district's Internet website; or (2) submit the updated information to the agency for posting on the agency's Internet website in accordance with Subsection (b). (d) A school district shall annually submit to the agency the information required under Subsection (a) for each member of the district's board of trustees. The information must: (1) identify the member designated as chair; and (2) be updated as required by Subsection (c). (e) The commissioner may adopt rules as necessary to implement this section.",
 "cross_refs": [
  "Educ. Code \u00a711.1518(a)",
  "Educ. Code \u00a711.1518(b)",
  "Educ. Code \u00a711.1518(c)"
 ],
 "defined_terms": [],
 "_note": "No defined terms explicitly defined in this section. Cross-references are internal subsection references. Source text is complete."
}