{
 "conflict": false,
 "severity": 0,
 "rationale": "The proposed homestead exemption increase under Tax Code \u00a711.13(b) concerns property tax appraisal and bears no relation to Educ. Code \u00a725.151, which governs student religious expression in school districts.",
 "quote": "A school district shall treat a student's voluntary expression of a religious viewpoint, if any, on an otherwise permissible subject in the same manner the district treats a student's voluntary expression of a secular or other viewpoint on an otherwise permissible subject and may not discriminate against the student based on a religious viewpoint expressed by the student on an otherwise permissible subject.",
 "_note": "No overlap between proposed change (property tax homestead exemption) and rule text (student religious expression)."
}