{
 "conflict": false,
 "severity": 0,
 "rationale": "Elec. Code \u00a7274.004 governs ballot ordering for constitutional amendments. It does not address homestead exemption amounts and imposes no constraint on the proposed increase.",
 "quote": "A proposed constitutional amendment must be placed on the ballot before all other propositions.",
 "_note": "No conflict. If the homestead increase requires a constitutional amendment, this section would govern ballot placement but would not block or constrain the policy change."
}